kda_ab_toolkit/__init__.py
kda_ab_toolkit/core.py
kda_ab_toolkit-0.1.6.dist-info/METADATA
kda_ab_toolkit-0.1.6.dist-info/WHEEL
kda_ab_toolkit-0.1.6.dist-info/top_level.txt
kda_ab_toolkit-0.1.6.dist-info/RECORD
